synthpix/__init__.py
synthpix/apply.py
synthpix/data_generate.py
synthpix/generate.py
synthpix/make.py
synthpix/sanity.py
synthpix/types.py
synthpix/utils.py
synthpix/data_sources/__init__.py
synthpix/data_sources/adapter.py
synthpix/data_sources/base.py
synthpix/data_sources/episodic.py
synthpix/data_sources/hdf5.py
synthpix/data_sources/mat.py
synthpix/data_sources/numpy.py
synthpix/sampler/__init__.py
synthpix/sampler/base.py
synthpix/sampler/real.py
synthpix/sampler/synthetic.py
synthpix/scheduler/__init__.py
synthpix/scheduler/base.py
synthpix/scheduler/episodic.py
synthpix/scheduler/hdf5.py
synthpix/scheduler/mat.py
synthpix/scheduler/numpy.py
synthpix/scheduler/prefetch.py
synthpix/scheduler/protocol.py
synthpix-0.1.2.dist-info/licenses/LICENSE
synthpix-0.1.2.dist-info/METADATA
synthpix-0.1.2.dist-info/WHEEL
synthpix-0.1.2.dist-info/top_level.txt
synthpix-0.1.2.dist-info/RECORD
