Metadata-Version: 2.4
Name: synthpix
Version: 0.1.2
Summary: A lightspeed PIV images generator using JAX
Author-email: Antonio Terpin <aterpin@ethz.ch>, Alan Bonomi <abonomi@ethz.ch>, Francesco Banelli <fbanelli@ethz.ch>
License: MIT
Project-URL: Homepage, https://github.com/antonioterpin/synthpix
Project-URL: Repository, https://github.com/antonioterpin/synthpix
Project-URL: Documentation, https://github.com/antonioterpin/synthpix#readme
Project-URL: Issues, https://github.com/antonioterpin/synthpix/issues
Keywords: PIV,synthetic data,jax
Classifier: Development Status :: 4 - Beta
Classifier: Intended Audience :: Science/Research
Classifier: Intended Audience :: Developers
Classifier: License :: OSI Approved :: MIT License
Classifier: Operating System :: OS Independent
Classifier: Programming Language :: Python :: 3
Classifier: Programming Language :: Python :: 3.10
Classifier: Programming Language :: Python :: 3.11
Classifier: Programming Language :: Python :: 3.12
Classifier: Topic :: Scientific/Engineering :: Artificial Intelligence
Classifier: Topic :: System :: Logging
Requires-Python: >=3.10
License-File: LICENSE
Requires-Dist: jax>=0.6.0
Requires-Dist: tqdm>=4.67.1
Requires-Dist: h5py>=3.13.0
Requires-Dist: ruamel.yaml>=0.18.10
Requires-Dist: Pillow>=10.0.0
Requires-Dist: robo-goggles>=0.1.7
Requires-Dist: numpy>=2.2.6
Requires-Dist: gdown>=5.2.0
Requires-Dist: grain>=0.2.13
Requires-Dist: orbax-checkpoint>=0.11.31
Provides-Extra: dev
Requires-Dist: pytest>=7.0.0; extra == "dev"
Requires-Dist: pytest-cov>=4.0.0; extra == "dev"
Requires-Dist: hypothesis>=6.0.0; extra == "dev"
Requires-Dist: snowballstemmer==2.2.0; extra == "dev"
Requires-Dist: pre_commit==4.0.1; extra == "dev"
Requires-Dist: tomli; extra == "dev"
Requires-Dist: pyupgrade>=3.19.0; extra == "dev"
Requires-Dist: matplotlib>=3.10.1; extra == "dev"
Requires-Dist: ruff>=0.9.0; extra == "dev"
Requires-Dist: mypy>=1.14.0; extra == "dev"
Provides-Extra: cuda12
Requires-Dist: jax[cuda12]>=0.6.0; extra == "cuda12"
Provides-Extra: download
Requires-Dist: gdown>=5.1.0; extra == "download"
Requires-Dist: scipy>=1.10.0; extra == "download"
Requires-Dist: tensorflow-cpu>=2.15.0; extra == "download"
Dynamic: license-file
